apibean/__init__.py
apibean-0.0.1.dist-info/LICENSE.txt
apibean-0.0.1.dist-info/METADATA
apibean-0.0.1.dist-info/WHEEL
apibean-0.0.1.dist-info/top_level.txt
apibean-0.0.1.dist-info/RECORD
